accessibility/__init__.py
accessibility/admin.py
accessibility/apps.py
accessibility/context_processors.py
accessibility/models.py
accessibility/tests.py
accessibility/urls.py
accessibility/views.py
accessibility/migrations/0001_initial.py
accessibility/migrations/__init__.py
aioa_accessibility/__init__.py
aioa_accessibility/asgi.py
aioa_accessibility/settings.py
aioa_accessibility/urls.py
aioa_accessibility/wsgi.py
django_all_in_one_accessibility-1.7.dist-info/METADATA
django_all_in_one_accessibility-1.7.dist-info/WHEEL
django_all_in_one_accessibility-1.7.dist-info/top_level.txt
django_all_in_one_accessibility-1.7.dist-info/RECORD
