Metadata-Version: 2.1
Name: django-all-in-one-accessibility
Version: 1.7
Summary: All in One Accessibility widget makes it easy for users to customize their experience in a single click tap or press of a button
Home-page: https://www.skynettechnologies.com
Author: Skynet Technologies USA LLC
Author-email: Skynet Technologies USA LLC <developer3@skynettechnologies.com>
Classifier: Programming Language :: Python :: 3
Classifier: Environment :: Web Environment
Classifier: Framework :: Django
Classifier: Framework :: Django :: 3.2  
Classifier: Intended Audience :: Developers
Classifier: License :: OSI Approved :: BSD License
Classifier: Operating System :: OS Independent
Classifier: Programming Language :: Python
Classifier: Programming Language :: Python :: 3
Classifier: Programming Language :: Python :: 3 :: Only
Classifier: Programming Language :: Python :: 3.8
Classifier: Programming Language :: Python :: 3.9
Classifier: Topic :: Internet :: WWW/HTTP
Classifier: Topic :: Internet :: WWW/HTTP :: Dynamic Content
Requires-Python: >=3.8
Requires-Dist: Django (>=3.2)
